Metadata-Version: 2.1
Name: django-oss-storage-for-dj4.0
Version: 1.1.2
Summary: Django Aliyun OSS (Object Storage Service) storage, bug fix, can be used in django4.0
Home-page: https://www.aliyun.com/product/oss
Author: uninterester
Author-email: 593626544@qq.com
License: UNKNOWN
Platform: UNKNOWN
Classifier: Development Status :: 5 - Production/Stable
Classifier: Intended Audience :: Developers
Classifier: License :: OSI Approved :: MIT License
Classifier: Operating System :: OS Independent
Classifier: Programming Language :: Python
Classifier: Programming Language :: Python :: 2
Classifier: Programming Language :: Python :: 2.6
Classifier: Programming Language :: Python :: 2.7
Classifier: Programming Language :: Python :: 3
Classifier: Programming Language :: Python :: 3.3
Classifier: Programming Language :: Python :: 3.4
Classifier: Programming Language :: Python :: 3.5
Classifier: Programming Language :: Python :: 3.6
Classifier: Framework :: Django
License-File: LICENSE
